{
  "fluentMethods": true,
  "clientRootFolder": "",
  "relationships": [],
  "fields": [
    {
      "fieldName": "libelle",
      "fieldType": "String"
    },
    {
      "fieldName": "terme",
      "fieldType": "String"
    },
    {
      "fieldName": "concept",
      "fieldType": "String"
    }
  ],
  "changelogDate": "20201126102012",
  "dto": "mapstruct",
  "searchEngine": "elasticsearch",
  "service": "serviceImpl",
  "entityTableName": "discipline",
  "databaseType": "sql",
  "readOnly": false,
  "jpaMetamodelFiltering": true,
  "pagination": "pagination"
}
